Workbook

Sheet Capex note
A2: MMRL-GREATER NOIDA : CAPEX NOTE No. : MMRP.CCDL.04.07 | O2: Date: 20th August'2017
A4: TITLE / HEAD | C4: Air Compressor
A5: ITEM / SERVICE REQUIRED | C5: 60 CFM Compressor with VFD, Air dryer with 1000L Air receiver unit.
A7: PURPOSE / JUSTIFICATION | C7: As per the process requirement in the collection centre, moisture free compressed air is required to operate most of the depollution and dismantling equipment. Also for smooth operation of pneumatic operated equipment's, Air receiver unit is required.
A9: DESIGN SPECIFICATION | C9: 60 CFM Compressor with VFD, Air dryer and 1000L Air receiver. Compressed air requirement calculation sheet is attached as 'Annexure 1'.
A11: ROUND OF NEGOTIATIONS | C11: Final round of negotiation done at Delhi office (Mahindra Towers) on August 3, 2017.
A13: SITE VISIT / ASSESSMENT | C13: Gardner Denver (Comp-Air) installations visited in Greater Noida (Lemon mobiles, Laxmi Fab Dye Printing P Ltd & Plistering Electronics) on August 4, 2017. Already using Elgi and Atlas Copco compressor in other MIL locations.
A15: OTHER FACTORS | C15: We are using Comp-air (Gardner Denver) compressor at our MME Sharjah , plant from last 5 years and have received a positive feedback on the smooth operation and maintenance of the said make compressor.
A17: No of Company | C17: 5
A18: No of Revisions | C18: 4
A20: + | C20: Atlas Copco / Vedant & Innovative | G20: ELGI | I20: IR / Aircon | K20: Gardner Denver / Maxon Engineering | O20: Kaeser / Laxmi
A21: OFFERS | C21: R0 | D21: R1 | E21: R2 | F21: R3 | G21: R0 | H21: R1 | I21: R0 | J21: R1 | K21: R0 | M21: R1 | N21: R2 | O21: R0 | P21: R1
A22: REFERENCES | C22: 04.05.17 | D22: VESSPL/SBKMSCL/1362 05.05.17 | E22: VESSPL/MM/16 05.08.17 | F22: SDS/2017/38 07.08.17 | G22: 231F496 18.04.17 | H22: 231F496 07.08.17 | I22: AE/000329/HSK 28.07.17 | J22: PI 05.08.17 | K22: GD-229R 23.07.17 | M22: GD-229R 03.08.17 | N22: GD-229R1 07.08.17 | O22: QTN/17/KC/030/MahMSTC 17.07.17 | P22: KC/DEL/73/SG 03.08.17
A23: BASIC VALUE (INR)/RATE (INR) | C23: ='Annx- 4 Comm comparison'!C16/100000 -> 9.1 | D23: ='Annx- 4 Comm comparison'!D16/100000 -> 8.99 | E23: ='Annx- 4 Comm comparison'!E16/100000 -> 6.45 | F23: ='Annx- 4 Comm comparison'!F16/100000 -> 6.076 | G23: ='Annx- 4 Comm comparison'!G16/100000 -> 9.481 | H23: ='Annx- 4 Comm comparison'!H16/100000 -> 5.58285 | I23: ='Annx- 4 Comm comparison'!I16/100000 -> 8.762 | J23: ='Annx- 4 Comm comparison'!J16/100000 -> 5.747 | ... P23: ='Annx- 4 Comm comparison'!P16/100000 -> 5.5195
A24: QUANTITY/JOB
A25: GST Value (INR) | C25: ='Annx- 4 Comm comparison'!C17/100000 -> 2.338 | D25: ='Annx- 4 Comm comparison'!D17/100000 -> 2.1632 | E25: ='Annx- 4 Comm comparison'!E17/100000 -> 1.546 | F25: ='Annx- 4 Comm comparison'!F17/100000 -> 1.47868 | G25: ='Annx- 4 Comm comparison'!G17/100000 -> 2.37908 | H25: ='Annx- 4 Comm comparison'!H17/100000 -> 1.413888 | I25: ='Annx- 4 Comm comparison'!I17/100000 -> 2.28482 | J25: ='Annx- 4 Comm comparison'!J17/100000 -> 1.49876 | ... P25: ='Annx- 4 Comm comparison'!P17/100000 -> 1.40851
A26: A | B26: TRANSPORTATION ,P&F, FREIGHT & INSURANCE COST | C26: ='Annx- 4 Comm comparison'!C19/100000 -> 0.34314 | D26: ='Annx- 4 Comm comparison'!D19/100000 -> 0.334596 | E26: ='Annx- 4 Comm comparison'!E19/100000 -> 0.07996 | F26: ='Annx- 4 Comm comparison'!F19/100000 -> 0.18228 | G26: ='Annx- 4 Comm comparison'!G19/100000 -> 0.3558024 | H26: ='Annx- 4 Comm comparison'!H19/100000 -> 0.1674855 | I26: ='Annx- 4 Comm comparison'!I19/100000 -> 0.3314046 | J26: 0 | K26: At actual | L26: At actual | M26: At actual | N26: ='Annx- 4 Comm comparison'!N18/100000 -> 0.1 | O26: ='Annx- 4 Comm comparison'!O19/100000 -> 0.162896 | P26: 0
A27: B | B27: INSTALLATION / E&C | C27: Addl. | D27: ='Annx- 4 Comm comparison'!D20/100000 -> 0.1 | E27: ='Annx- 4 Comm comparison'!E20/100000 -> 0.05 | F27: Addl. | G27: Addl. | H27: Addl. | I27: Addl | J27: 0 | K27: Addl | L27: Addl | M27: Addl | N27: Inclusive | O27: 0 | P27: 0
A28: C | B28: GST @ 18 % on (A+B) | C28: =(C26)*18% -> 0.0617652 | D28: =(D27+D26)*18% -> 0.07822728 | E28: =(E27+E26)*18% -> 0.0233928 | F28: =(F26)*18% -> 0.0328104 | G28: =(G26)*18% -> 0.064044432 | H28: =(H26)*18% -> 0.03014739 | I28: =(I26)*18% -> 0.059652828 | J28: 0 | K28: Addl | L28: Addl | M28: Addl | N28: =(N26)*18% -> 0.018 | O28: =O27*18% -> 0 | P28: =P27*18% -> 0
A29: TOTAL COST (INR) | C29: =SUM(C23:C28) -> 11.842905 | D29: =SUM(D23:D28) -> 11.666023 | E29: =SUM(E23:E28) -> 8.1493528 | F29: =SUM(F23:F28) -> 7.7697704 | G29: =SUM(G23:G28) -> 12.279927 | H29: =SUM(H23:H28) -> 7.1943709 | I29: =SUM(I23:I28) -> 11.437877 | J29: =SUM(J23:J28) -> 7.24576 | ... P29: =SUM(P23:P28) -> 6.92801
A30: DELIVERY / EX-WORKS | C30: 6 weeks / Pune | G30: 4 weeks / Coimbatore | I30: 4 weeks / Ahmedabad | K30: 4 weeks / Ahmedabad | O30: 2 weeks / Pune
A31: STATUS | C31: - | D31: - | E31: - | F31: L5 | G31: - | H31: L3 | I31: - | J31: L4 | K31: - | L31: - | M31: - | N31: L1 | O31: - | P31: L2
A32: All values in Lacs of INR
A34: COMMERCIAL TERMS: As per final offer (Ref.GD-229R1 dated 07.08.17) of Maxon Engineers (Gardner Denver)
A35: PAYMENT TERMS | C35: 90% against receipt of materrial within 7 day and Balance 10% after satisafactory installation and commissioning and FAC or within 30 days after receipt of material whichever is earlier.
A36: P & F | C36: Nil
A37: DELIVERY BY | C37: Mid-September, 2017
A38: WARRANTY | C38: 5 years warranty on compressor, subject to warranty agreement
A40: ATTACHMENTS | C40: Annexure 2:- Techno commercial offers from all suppliers i.e Vedant equipsales,Innovative engineering, Maxon engineering , Elgi, Kaeser, Aircon Engineers
C41: Annexure 3:-Technical comparison
C42: Annexure 4:-Commercial comparison
A44: RECOMMENDATIONS | C44: We recommend to procure 'Garden Denver' make compressor from Maxon Engineering, Greater Noida at gross cost of Rs.5,83,319/-(Five lakhs eighty-three thousand three hundred and nineteen only).
A45: INITIATED BY
B50: MILIND PATIL | E50: LAXMAN POPALGHAT | K50: AMITAVA SINHA
A51: APPROVED BY
B55: VIJAY ARORA | E55: PERCY MAHERNOSH | K55: SUMIT ISSAR

Sheet Summary
D3: Qty (No) | E3: Description | F3: INR
D4: 1 | E4: Gardner Denver Model “L11RS-7.5A” FAD 65cfm, Oil Lubricated, Air Cooled, Variable Speed Motor Driven Rotary Screw Compressor for standard scope of supply as described in the subject offer. | F4: 2,99,000
D5: 1 | E5: Gardner Denver Refrigerated Type Dryer Model “GD80” Capacity 80cfm Max. working pressure – 16kg | F5: 75000
D6: 1 | E6: GARDNER DENVER Pre Filter – 05 Micron, 150 CFM, Model – G250P | F6: 15000
D7: 1 | E7: GARDNER DENVER Post Filter – 01 Micron, 150 CFM, Model – G250X | F7: 15000
D8: 1 | E8: 01 No. AIR RECEIVER TANK – 1000 Liters | F8: 50000
D9: 1 | E9: AUTO DRAIN VALVE FOR RECEIVER TANK – 230 VAC | F9: 4999

Sheet Annx-1
B1: Annexure - I
A3: Equipment | B3: Particulars | C3: Quantity | D3: Max flow required as per OEM | F3: Practical consumption | H3: Remarks
D4: LPM | E4: CFM | F4: LPM | G4: CFM
A5: Fluid drainage system- 2 nos | B5: 4 vacuum pumps, one drill and Shock absorber drill | C5: PV: 2 nos. CV: 1 no. | D5: =1000*3 -> 3000 | E5: =D5*0.03531 -> 105.93 | F5: 800 | G5: =F5*0.03531 -> 28.248 | H5: We are taking 3 units of fuel drainage system , 2 nos for ELV and 1 Nos for HCV. In one unit at a time we will operating 2 pumps and drill bit
A6: Petrol/diesel removal | D6: 500 | E6: =D6*0.03531 -> 17.655 | F6: 300 | G6: =F6*0.03531 -> 10.593 | H6: We are taking 2 units of diesel/petrol removal system . In one unit at a time we will operating 1 pumps and drill bit
A7: Tank - 3pumps | D7: 600 | E7: =D7*0.03531 -> 21.186 | F7: 0 | G7: =F7*0.03531 -> 0 | H7: It will be used once as per vehicle
A8: LPG/CNG recovery | D8: 200 | E8: =D8*0.03531 -> 7.062 | F8: 0 | G8: =F8*0.03531 -> 0 | H8: It will be done lot basis
A9: Tyre removal without damage | D9: 300 | E9: =D9*0.03531 -> 10.593 | F9: 300 | G9: =F9*0.03531 -> 10.593 | H9: It will operate regular
A10: Hand tools 8 nos | D10: =594*8/4 -> 1188 | E10: =D10*0.03531 -> 41.94828 | F10: 300 | G10: =F10*0.03531 -> 10.593 | H10: We have considered Tools operating and cleaning parts at a time. Tools CFM taken from Chicago pnuematic tools manual
E11: =SUM(E5:E10) -> 204.37428 | G11: =SUM(G5:G10) -> 60.027
A12: Considering 80% loading | G12: =G11*0.8 -> 48.0216
A13: Compressor recommended | G13: 60 CFM

Sheet Annx-3 Tech comparision
A1: ANNEXURE 3'
A3: Technical Comparison for 60 cfm Air Compressor
A5: Sn | B5: Specifications | C5: Atlas copco | D5: ELGI | E5: IR | F5: Gardner denver | G5: Kaeser
A6: 1 | B6: CFM rating of compressor | C6: 65.1 | D6: 73 | E6: 56.5 cfm | F6: 65 cfm | G6: 69.94
A7: 2 | B7: Make | C7: Atlas copco | D7: Elgi | E7: IR | F7: Gardner denver | G7: Keser
A8: 3 | B8: Model | C8: GA 11 VSD | D8: EG 11-7.5 | E8: UP5-15-10-VFD | F8: L11RS-7.5A | G8: SK 22 T SFC
A9: 4 | B9: Working pressure (bar) | C9: 7.5 | D9: 7 | E9: 8 | F9: 7.5 | G9: 7.5
A10: 5 | B10: Motor rating (Kw/Hp) | C10: 11 Kw | D10: 11 Kw | E10: 15 Kw | F10: 11 Kw | G10: 11 kw
A11: 6 | B11: Motor class | C11: IE4 | D11: TEFC | E11: TEFC | F11: IE3 | G11: IE3
A12: 7 | B12: Motor cooling | C12: Oil | D12: Air cooled | E12: Air cooled | F12: Air cooled | G12: Air cooled
A13: 8 | B13: Drive to compressor | C13: Direct coupled | D13: Through gear | E13: Belt drive | F13: Belt drive | G13: Direct coupled
A14: 9 | B14: VFD available Yes/ No | C14: Y | D14: Y | E14: Y | F14: Y | G14: Y
A15: 10 | B15: VFD Model | C15: Atlas copco | D15: _ | E15: _ | F15: Allen Bradley | G15: Siemens
A16: 11 | B16: VFD rating | C16: _ | D16: _ | E16: _ | F16: Suitable to motor | G16: _
A17: 12 | B17: Air dryer rating | C17: In-built | D17: 100 cfm | E17: In-built | F17: 80 Cfm | G17: In-built
A18: 13 | B18: Refrigerant | C18: _ | D18: _ | E18: R134a | F18: R134a | G18: R134a
A19: 14 | B19: Air reciever capacity (L) | C19: 1000 | D19: 1000 | E19: 1000 | F19: 1000 | G19: 1000
A20: 15 | B20: Air reciever max pressure (Kg/cm2) | C20: _ | D20: _ | E20: 12 | F20: 12 | G20: _
A21: 16 | B21: Pre filter | C21: details not given | D21: 1 micron | E21: 1 micron | F21: 1/5 micron | G21: details not given
A22: 17 | B22: Fine filter | C22: details not given | D22: .01 micron | E22: .01 micron | F22: 01/0.01 micron | G22: details not given
A23: 18 | B23: HMI | C23: Y | D23: Y | E23: _ | F23: Y | G23: Y
A24: 19 | B24: Dimension of Set in acoustic enclosure (L X W X H) mm | C24: _ | D24: 1425 X 720 X 1470 | E24: _ | F24: 667 X 630 X 1050 | G24: 750 X 1240 X 1260
A25: 20 | B25: Weight of compressor in (Kgs). | C25: 278 | D25: 612 | E25: _ | F25: 219 kg & dryer weight separate | G25: 404
A26: 21 | B26: Type of cooling | C26: _ | D26: Air cooled | E26: _ | F26: Air cooled | G26: Air cooled
A27: 22 | B27: Compressor max RPM | C27: _ | D27: _ | E27: _ | F27: 6700 | G27: 3552
A28: 23 | B28: Compressor min RPM | C28: _ | D28: _ | E28: _ | F28: 2313 | G28: 1184
A29: 24 | B29: Max. ambient temperature (degree celcius) | C29: _ | D29: _ | E29: _ | F29: 48 | G29: 45
A30: 25 | B30: Noise level db(A) | C30: 73 | D30: 69 | E30: 68 | F30: 70 | G30: 67
A31: 26 | B31: Drain valve | C31: _ | D31: Zero air loss | E31: _ | F31: _ | G31: _

Sheet Annx- 4 Comm comparison
A1: 'ANNEXURE 4'
A3: Commercial comparison for 60 CFM Air compressor
A4: Sr No | B4: SUPPLIER | C4: ATLAS COPOCO | G4: ELGI | I4: IR | K4: GARDNER DENVER | O4: KAESER
C5: Innovative Engineering | D5: Vedant Equipment Sales | E5: Vedant Equipment Sales | F5: Innovative Engineering | I5: Aircon Engineers | K5: Maxon Engineering | O5: Laxmi tech, Nasik | P5: Kaeser Compressors (I) Pvt Ltd, Delhi
A6: A | B6: OFFERS | C6: R0 | D6: R1 | E6: R2 | F6: R1 | G6: R0 | H6: R1 | I6: R0 | J6: R1 | K6: R0 | M6: R1 | N6: R2 | O6: R0 | P6: R1
A7: B | B7: DATE | C7: 04.05.17 | D7: 05.05.17 | E7: 05.08.17 | F7: 07.08.17 | G7: 18.04.17 | H7: 07.08.17 | I7: 28.07.17 | J7: 05.08.17 | K7: 23.07.17 | M7: 03.08.17 | N7: 07.08.17 | O7: 17.07.17 | P7: 03.08.17
A8: C | B8: REFERENCES | C8: _ | D8: VESSPL/SBKMSCL/1362 | E8: VESSPL/MM/16 | F8: SDS/2017/38 | G8: 231F496 | H8: 231F496 | I8: AE/000329/HSK | J8: PI | K8: GD-229R | M8: GD-229R | N8: GD-229R1 | O8: UQN/KCIPL/LT/1025/2017 QTN/17/KC/030/MahMSTC | P8: KC/DEL/73/SG
A9: 1 | B9: Basic Cost of Supply of compressor (Rs) | C9: 700000 | D9: 545000 | E9: 385000 | F9: 385000 | G9: 672500 | H9: 408975 | I9: 640300 | J9: 420300 | K9: 525000 | L9: 415000 | M9: 299000 | N9: 299000 | O9: 581000 | P9: 415000
A10: 2 | B10: Basic Cost of VFD
A11: 3 | B11: Basic cost of air dryer | D11: 167000 | E11: 130000 | F11: 140700 | G11: 169000 | H11: 78225 | I11: 90700 | J11: 60000 | K11: 115000 | L11: 99000 | M11: 75000 | N11: 75000 | P11: 79680
A12: 4 | B12: Basic cost of air reciever | C12: 140000 | D12: 117000 | E12: 80000 | F12: 81900 | G12: 68600 | H12: 43785 | I12: 117400 | J12: 76400 | K12: 75000 | L12: 60000 | M12: 50000 | N12: 50000 | O12: 60000 | P12: 39840
A13: 5 | B13: Pre filter | C13: 70000 | D13: 70000 | E13: 50000 | F13: 0 | G13: 19000 | H13: 13650 | I13: 27800 | J13: 18000 | K13: 28000 | L13: 20000 | M13: 15000 | N13: 15000 | O13: NA | P13: 17430
A14: 6 | B14: Fine filter | C14: NA | D14: NA | E14: NA | F14: 0 | G14: 19000 | H14: 13650 | K14: 28000 | L14: 20000 | M14: 15000 | N14: 15000 | O14: NA | P14: NA
A15: 7 | B15: Auto darin valve for reciver | K15: Not mentioned | L15: Not mentioned | M15: 4999 | N15: 4999 | O15: NA | P15: 0
A16: 7 | B16: Total Basic Cost Rs. (compressor with VFD+Dryer+Air reciever) | C16: =SUM(C9:C15) -> 910000 | D16: =SUM(D9:D15) -> 899000 | E16: =SUM(E9:E15) -> 645000 | F16: =SUM(F9:F15) -> 607600 | G16: =SUM(G9:G15) -> 948100 | H16: =SUM(H9:H15) -> 558285 | I16: =SUM(I9:I15) -> 876200 | J16: =SUM(J9:J15) -> 574700 | ... P16: =SUM(P9:P15) -> 551950
A17: 8 | B17: GST@28% & 18% | C17: =(C9)*0.28+SUM(C11:C15)*0.18 -> 233800 | D17: =(D9)*0.28+SUM(D11:D15)*0.18 -> 216320 | E17: =(E9)*0.28+SUM(E11:E15)*0.18 -> 154600 | F17: =(F9)*0.28+SUM(F11:F15)*0.18 -> 147868 | G17: =(G9)*0.28+SUM(G11:G15)*0.18 -> 237908 | H17: =(H9)*0.28+SUM(H11:H15)*0.18 -> 141388.8 | I17: =(I9+I12)*0.28+(I11+I14)*0.18 -> 228482 | J17: =(J9+J12)*0.28+(J11+J14)*0.18 -> 149876 | K17: =(K9)*0.28+SUM(K11:K15)*0.18 -> 191280 | L17: =(L9)*0.28+SUM(L11:L15)*0.18 -> 152020 | M17: =(M9)*0.28+SUM(M11:M15)*0.18 -> 112519.82 | N17: =(N9)*0.28+SUM(N11:N15)*0.18 -> 112519.82 | O17: =(O9)*0.28+SUM(O11:O15)*0.18 -> 173480 | P17: =(P9)*0.28+SUM(P11:P15)*0.18 -> 140851
A18: 9 | B18: Transportation,P&F, Freight & Insurance Cost (Rs.) | C18: At actual | D18: At actual | E18: Additional | F18: Additional | G18: At actual | H18: At actual | I18: At actual | J18: 0 | K18: At actual | L18: At actual | M18: At actual | N18: 10000 | O18: At actual | P18: 0
A19: 10 | B19: Packing Forwarding cost(Rs.) | C19: =(C17+C16)*3% -> 34314 | D19: =(D17+D16)*3% -> 33459.6 | E19: =(E17+E16)*1% -> 7996 | F19: =(F16)*3% -> 18228 | G19: =(G17+G16)*3% -> 35580.24 | H19: =H16*3% -> 16748.55 | I19: =(I17+I16)*3% -> 33140.46 | J19: 0 | K19: Not mentioned | L19: Not mentioned | M19: NA | N19: NA | O19: =(O17+O16)*2% -> 16289.6 | P19: 0
A20: 11 | B20: Commissioning Assistance charges | C20: Additional | D20: 10000 | E20: 5000 | F20: 0 | G20: Additional | H20: Additional | I20: 2500 per day +taxes+to/Fro | J20: 0 | K20: Additional | L20: Additional | M20: 0 | N20: 0 | O20: Free 2 visits | P20: Free 2 visits
A21: 12 | B21: GST@18% | C21: =C19*0.18 -> 6176.52 | D21: =(D19+D20)*0.18 -> 7822.728 | E21: =(E19+E20)*0.18 -> 2339.28 | F21: =(F19+F20)*0.18 -> 3281.04 | G21: =(G19)*0.18 -> 6404.4432 | H21: =(H19)*0.18 -> 3014.739 | I21: =(I19)*0.18 -> 5965.2828 | J21: 0 | K21: _ | L21: _ | M21: =M20*0.18 -> 0 | N21: =N18*0.18 -> 1800 | O21: 0 | P21: 0
A22: 13 | B22: Landed cost on site | C22: =SUM(C16:C21) -> 1184290.5 | D22: =SUM(D16:D21) -> 1166602.3 | E22: =SUM(E16:E21) -> 814935.28 | F22: =SUM(F16:F21) -> 776977.04 | G22: =SUM(G16:G21) -> 1227992.7 | H22: =SUM(H16:H21) -> 719437.09 | I22: =SUM(I16:I21) -> 1143787.7 | J22: =SUM(J16:J21) -> 724576 | ... P22: =SUM(P16:P21) -> 692801
A23: 14 | B23: Delivery Period | C23: 6-8 week | D23: 4-6 week | E23: 4-6 week | F23: 6 week | G23: 4 weeks | H23: 4 weeks | I23: 6-8 week | J23: 4 weeks | K23: 4 weeks | L23: 4 weeks | M23: 4 weeks | N23: 4 weeks | O23: 10 to 12 week | P23: ex stock
A24: 15 | B24: Delivery From | C24: Pune | D24: Pune | E24: Pune | F24: Pune | G24: Coimbatore | H24: Coimbatore | I24: Ahmedabad | J24: Ahmedabad | K24: Ahmedabad | L24: Ahmedabad | M24: Ahmedabad | N24: Ahmedabad | O24: Pune | P24: Pune
A25: 16 | B25: Period of warranty | C25: 12 month from commisioning / 18 from dispatch or 4000 running hours | D25: 12 month from commisioning / 18 from dispatch or 4000 running hours | E25: 12 month from commisioning / 18 from dispatch or 4000 running hours | F25: 12 month from commisioning / 18 from dispatch or 4000 running hours | G25: 36 month from commisioning / 48 from dispatch | H25: 72 month for airend & 36 month from commisioning / 48month from dispatch for motor/tank/cooler | I25: 12 month from commisioning / 18 from dispatch | J25: 12 month from commisioning / 18 from dispatch | K25: 12 month from commisioning / 18 from dispatch | L25: 12 month from commisioning / 18 from dispatch | M25: 5 years with contractual agreement | N25: 5 years with contractual agreement | O25: 12 month from commisioning / 18 from dispatch | P25: 12 month from commisioning / 18 from dispatch
A26: 17 | B26: Terms Of Payment | C26: 30% advance and balance aginst proforma | D26: 30% advance and balance aginst proforma | E26: 90% against delivery within 7 day and 10% after instalation or within 30 days after reciept of material | F26: 30% advance and balance aginst proforma | G26: 30% advance and balance aginst proforma | H26: 30% advance and balance aginst proforma | I26: 35% advance and balance aginst proforma | J26: 90% against delivery within 7 day and 10% after installation or within 30 days after reciept of material | K26: 50% advance and balance aginst proforma | L26: 50% advance and balance aginst proforma | M26: 90% against delivery within 7 day and 10% after installation or within 30 days after reciept of material | N26: 90% against delivery within 7 day and 10% after installation or within 30 days after reciept of material | O26: 30% advance and balance aginst proforma | P26: 90% against delivery within 7 day and 10% after installation or within 30 days after reciept of material
A27: 18 | B27: Offer Validity | C27: 30 days | D27: 30 days | E27: 30 days | F27: 30 days | G27: 45 days | H27: 45 days | I27: 30 days | L27: 30 days | O27: 30 days | P27: 30 days
A28: 19 | B28: Contact Person | C28: Bhusan Bokil | D28: Sudhakar Kadam 9922929065 | F28: Sunil 9818337429 | G28: Kedar Joshi # 9967701572 | I28: Vijay # 9810077143 | L28: Rajiv Kumar # 9810330920 | O28: Sanjay Gupta # 9818398983

Sheet Summ-Commercial
B1: Summary - Commercial
B3: SUPPLIERS / SERVICE PROVIDER | C3: Atlas Copco (Innovative engg) | E3: Atlas Copco (Vedant equip sales) | G3: ELGI | I3: IR (Aircon Engineer) | K3: Gardner Denver (Maxon Engg) | N3: Kaeser
B4: Offer | C4: R0 | D4: R1 | E4: R0 | F4: R1 | G4: R0 | H4: R1 | I4: R0 | J4: R1 | K4: R0 | L4: R1 | M4: R2 | N4: R0 | O4: R1
B5: PRICE QUOTE
B6: Basic Value (INR) | C6: 9.1 | D6: 6.076 | E6: 9.04 | F6: 6.45 | G6: 9.481 | H6: 5.582 | I6: 8.76 | J6: 5.747 | K6: ='Annx- 4 Comm comparison'!L16/100000 -> 6.14 | L6: ='Annx- 4 Comm comparison'!M16/100000 -> 4.58999 | M6: ='Annx- 4 Comm comparison'!N16/100000 -> 4.58999 | N6: 6.41 | O6: 5.52
B7: GST@28% & 18% | C7: 2.34 | D7: 1.478 | E7: 2.177 | F7: 1.546 | G7: 2.38 | H7: 1.41 | I7: 2.28 | J7: 1.498 | K7: 1.927 | L7: 1.125 | M7: 1.125 | N7: 1.7348 | O7: 1.408
B8: Transportation , Freight & Insurance Cost | C8: At actual | E8: At actual | G8: At actual | I8: At actual | J8: 0 | K8: At actual | L8: At actual | M8: ='Annx- 4 Comm comparison'!N18/100000 -> 0.1 | N8: At actual | O8: 0
B9: Installation / E&C | C9: Addl. | D9: Addl. | E9: Addl. | F9: 0.05 | G9: Addl. | H9: Addl. | I9: Addl. | J9: 0 | K9: Addl. | L9: 0 | M9: 0 | N9: 0 | O9: 0
B10: GST @ 18 % | C10: Addl. | D10: Addl. | E10: Addl. | F10: =F9*18% -> 0.009 | G10: Addl. | H10: Addl. | I10: Addl. | J10: 0 | K10: Addl. | L10: 0 | M10: 0 | N10: =N9*18% -> 0 | O10: =O9*18% -> 0
B11: Total Landed Cost | C11: =SUM(C6:C10) -> 11.44 | D11: =SUM(D6:D10) -> 7.554 | E11: =SUM(E6:E10) -> 11.217 | F11: =SUM(F6:F10) -> 8.055 | G11: =SUM(G6:G10) -> 11.861 | H11: =SUM(H6:H10) -> 6.992 | I11: =SUM(I6:I10) -> 11.04 | J11: =SUM(J6:J10) -> 7.245 | ... O11: =SUM(O6:O10) -> 6.928
B12: Delivery | C12: 6 weeks | E12: 6 weeks | G12: 4 weeks | I12: 4 weeks | K12: 4 weeks | N12: 2 weeks
B13: All values in Lacs of INR
